{
  "0": "Standing - Straight",
  "1": "Standing - Forward bend",
  "2": "Standing - Side bend",
  "3": "Standing - Others",
  "4": "Sitting - Normal1 (legs in front)",
  "5": "Sitting - Normal2 (legs behind)",
  "6": "Sitting - Split",
  "7": "Sitting - Forward bend",
  "8": "Sitting - Twist",
  "9": "Balancing - Front",
  "10": "Balancing - Side",
  "11": "Inverted - Legs straight up",
  "12": "Inverted - Legs bend",
  "13": "Reclining - Up-facing",
  "14": "Reclining - Down-facing",
  "15": "Reclining - Side facing",
  "16": "Reclining - Plank balance",
  "17": "Wheel - Up-facing",
  "18": "Wheel - Down-facing",
  "19": "Wheel - Others"
}
